{
    "val": [
        {
            "prompt_text": "Hidde's bench was at Hidde's highway, today. 18 bench were found at park. 5 bench were found at water. Hidde's bench",
            "correct_answer": "highway",
            "prediction": "5 bench were found at water."
        },
        {
            "prompt_text": "Hidde's bench was at Hidde's highway, 1 days ago. Nihed's bench was at Nihed's garage, today. 18 bench were found at park. 6 bench were found at highway. Hidde's bench",
            "correct_answer": "highway",
            "prediction": "was at Hidde's highway"
        },
        {
            "prompt_text": "Nihed's bench was at Nihed's garage, 1 days ago. Fajjaaz's boat was at Fajjaaz's university, today. 18 bench were found at park. 6 bench were found at highway. Nihed's bench",
            "correct_answer": "garage",
            "prediction": "was at Nihed's garage, 1 days ago."
        },
        {
            "prompt_text": "Fajjaaz's boat was at Fajjaaz's university, 1 days ago. Hidde's person was at Hidde's garage, today. 19 person were found at university. 3 person were found at garage. Hidde's person",
            "correct_answer": "garage",
            "prediction": "was at Hidde's garage"
        },
        {
            "prompt_text": "Hidde's person was at Hidde's garage, 1 days ago. Nicole's car was at Nicole's garage, today. 18 bench were found at park. 6 bench were found at highway. Nihed's bench",
            "correct_answer": "garage",
            "prediction": "was at Nihed's garage, today."
        },
        {
            "prompt_text": "Nicole's car was at Nicole's garage, 1 days ago. Nicole's motorcycle was at Nicole's garage, today. 11 car were found at garage. 3 car were found at university. Nicole's car",
            "correct_answer": "garage",
            "prediction": "was at Nicole's garage, 1 days ago. Nicole's motorcycle was at Nicole'"
        },
        {
            "prompt_text": "Nicole's motorcycle was at Nicole's garage, 1 days ago. Nihed's airplane was at Nihed's sky, today. 24 motorcycle were found at garage. 4 motorcycle were found at station. Nicole's motorcycle",
            "correct_answer": "garage",
            "prediction": "Nicole's motorcycle was at Nicole's garage, 1 days ago. Nihed'"
        },
        {
            "prompt_text": "Nihed's airplane was at Nihed's sky, 1 days ago. Nihed's truck was at Nihed's university, today. 18 bench were found at park. 6 bench were found at highway. Nihed's bench",
            "correct_answer": "garage",
            "prediction": "was at Nihed's park, today."
        },
        {
            "prompt_text": "Nihed's truck was at Nihed's university, 1 days ago. Hidde's boat was at Hidde's water, today. 16 boat were found at water. 3 boat were found at university. Hidde's boat",
            "correct_answer": "water",
            "prediction": "was at Hidde's water, today."
        },
        {
            "prompt_text": "Hidde's boat was at Hidde's water, 1 days ago. Nicole's motorcycle was at Nicole's garage, today. 19 person were found at university. 4 person were found at garage. Hidde's person",
            "correct_answer": "garage",
            "prediction": "was found at water."
        },
        {
            "prompt_text": "Nicole's motorcycle was at Nicole's garage, 1 days ago. Nihed's car was at Nihed's university, today. 17 boat were found at water. 3 boat were found at university. Hidde's boat",
            "correct_answer": "water",
            "prediction": "was at Hidde's university, today."
        },
        {
            "prompt_text": "Nihed's car was at Nihed's university, 1 days ago. Taewoon's bicycle was at Taewoon's garage, today. 19 airplane were found at sky. 4 airplane were found at station. Nihed's airplane",
            "correct_answer": "sky",
            "prediction": "was at Nihed's university, 1 days ago. Taewoon's"
        },
        {
            "prompt_text": "Taewoon's bicycle was at Taewoon's garage, 1 days ago. Nihed's train was at Nihed's water, today. 19 airplane were found at sky. 4 airplane were found at station. Nihed's airplane",
            "correct_answer": "sky",
            "prediction": "was at Nihed's water, today."
        },
        {
            "prompt_text": "Nihed's train was at Nihed's water, 1 days ago. Nihed's airplane was at Nihed's sky, today. 9 truck were found at highway. 4 truck were found at garage. Nihed's truck",
            "correct_answer": "university",
            "prediction": "was at Nihed's water, 1 days ago. Nihed's airplane"
        },
        {
            "prompt_text": "Nihed's airplane was at Nihed's sky, 1 days ago. Taewoon's truck was at Taewoon's highway, today. 11 car were found at garage. 5 car were found at university. Nihed's car",
            "correct_answer": "university",
            "prediction": "1 car were found at university."
        },
        {
            "prompt_text": "Taewoon's truck was at Taewoon's highway, 1 days ago. Hidde's person was at Hidde's university, today. 11 truck were found at highway. 4 truck were found at garage. Taewoon's truck",
            "correct_answer": "highway",
            "prediction": "1 truck were found at highway. 4 truck were found at garage."
        },
        {
            "prompt_text": "Hidde's person was at Hidde's university, 1 days ago. Fajjaaz's train was at Fajjaaz's sky, today. 12 bicycle were found at garage. 3 bicycle were found at university. Taewoon's bicycle",
            "correct_answer": "garage",
            "prediction": "was at Taewoon's university, 1 days ago."
        },
        {
            "prompt_text": "Fajjaaz's train was at Fajjaaz's sky, 1 days ago. Nihed's boat was at Nihed's garage, today. 14 train were found at station. 7 train were found at water. Fajjaaz's train",
            "correct_answer": "sky",
            "prediction": "1 train at Fajjaaz's sky"
        },
        {
            "prompt_text": "Nihed's boat was at Nihed's garage, 1 days ago. Fajjaaz's bicycle was at Fajjaaz's sky, today. 11 car were found at garage. 5 car were found at university. Nicole's car",
            "correct_answer": "garage",
            "prediction": "was at Nicole's garage, 1 days ago."
        },
        {
            "prompt_text": "Fajjaaz's bicycle was at Fajjaaz's sky, 1 days ago. Nihed's motorcycle was at Nihed's station, today. 14 train were found at station. 7 train were found at water. Fajjaaz's train",
            "correct_answer": "sky",
            "prediction": "was at Fajjaaz's station, today."
        },
        {
            "prompt_text": "Nihed's motorcycle was at Nihed's station, 1 days ago. Nihed's bench was at Nihed's park, today. 14 train were found at station. 7 train were found at water. Nihed's train",
            "correct_answer": "water",
            "prediction": "was at Nihed's station, 1 days ago. Nihed's bench"
        },
        {
            "prompt_text": "Nihed's bench was at Nihed's park, 1 days ago. Nicole's bicycle was at Nicole's garage, today. 13 bicycle were found at garage. 3 bicycle were found at highway. Nicole's bicycle",
            "correct_answer": "garage",
            "prediction": "was at Nicole's garage, today."
        },
        {
            "prompt_text": "Nicole's bicycle was at Nicole's garage, 1 days ago. Fajjaaz's bicycle was at Fajjaaz's park, today. 17 boat were found at water. 4 boat were found at garage. Nihed's boat",
            "correct_answer": "garage",
            "prediction": "was at Nihed's water, today."
        },
        {
            "prompt_text": "Fajjaaz's bicycle was at Fajjaaz's park, 1 days ago. 14 bicycle were found at garage. 3 bicycle were found at park. Fajjaaz's bicycle",
            "correct_answer": "station",
            "prediction": "3 bicycle were found at park."
        },
        {
            "prompt_text": "Fajjaaz's bicycle was at Fajjaaz's station, 1 days ago. Nihed's truck was at Nihed's highway, today. 12 truck were found at highway. 4 truck were found at garage. Nihed's truck",
            "correct_answer": "highway",
            "prediction": "was at Nihed's highway"
        },
        {
            "prompt_text": "Nihed's truck was at Nihed's highway, 1 days ago. Fajjaaz's bus was at Fajjaaz's station, today. 14 bus were found at station. 3 bus were found at park. Fajjaaz's bus",
            "correct_answer": "station",
            "prediction": "was at Fajjaaz's station"
        },
        {
            "prompt_text": "Fajjaaz's bus was at Fajjaaz's station, 1 days ago. Fajjaaz's bench was at Fajjaaz's water, today. 13 truck were found at highway. 4 truck were found at garage. Nihed's truck",
            "correct_answer": "highway",
            "prediction": "was at Nihed's water, today."
        },
        {
            "prompt_text": "Fajjaaz's bench was at Fajjaaz's water, 1 days ago. Nicole's bicycle was at Nicole's highway, today. 20 bench were found at park. 7 bench were found at water. Nihed's bench",
            "correct_answer": "park",
            "prediction": "4 bench were found at water."
        },
        {
            "prompt_text": "Nicole's bicycle was at Nicole's highway, 1 days ago. Hidde's truck was at Hidde's station, today. 15 bus were found at station. 3 bus were found at park. Fajjaaz's bus",
            "correct_answer": "station",
            "prediction": "1 bus were found at park."
        },
        {
            "prompt_text": "Hidde's truck was at Hidde's station, 1 days ago. Fajjaaz's motorcycle was at Fajjaaz's garage, today. 20 bench were found at park. 7 bench were found at water. Nihed's bench",
            "correct_answer": "park",
            "prediction": "was at Nihed's station, 1 days ago."
        },
        {
            "prompt_text": "Fajjaaz's motorcycle was at Fajjaaz's garage, 1 days ago. Nihed's boat was at Nihed's water, today. 15 bus were found at station. 3 bus were found at park. Fajjaaz's bus",
            "correct_answer": "station",
            "prediction": "was at Fajjaaz's station, 1 days ago."
        },
        {
            "prompt_text": "Fajjaaz's motorcycle was at Fajjaaz's garage, today. 21 person were found at university. 4 person were found at garage. Hidde's person",
            "correct_answer": "university",
            "prediction": "was found at garage."
        },
        {
            "prompt_text": "Fajjaaz's motorcycle was at Fajjaaz's garage, 1 days ago. Hidde's airplane was at Hidde's sky, today. 14 train were found at station. 7 train were found at water. Fajjaaz's train",
            "correct_answer": "sky",
            "prediction": "was at Fajjaaz's station, 1 days ago. Hidde'"
        },
        {
            "prompt_text": "Hidde's airplane was at Hidde's sky, 1 days ago. Fajjaaz's person was at Fajjaaz's university, today. 14 bicycle were found at garage. 5 bicycle were found at highway. Nicole's bicycle",
            "correct_answer": "highway",
            "prediction": "5 bicycle were found at highway."
        },
        {
            "prompt_text": "Fajjaaz's person was at Fajjaaz's university, 1 days ago. Nihed's boat was at Nihed's highway, today. 14 train were found at station. 7 train were found at water. Nihed's train",
            "correct_answer": "water",
            "prediction": "was at Nihed's highway, today."
        },
        {
            "prompt_text": "Nihed's boat was at Nihed's highway, 1 days ago. Taewoon's motorcycle was at Taewoon's garage, today. 18 boat were found at water. 4 boat were found at garage. Nihed's boat",
            "correct_answer": "highway",
            "prediction": "was at Nihed's highway, 1 days ago. Taewoon's"
        },
        {
            "prompt_text": "Taewoon's motorcycle was at Taewoon's garage, 1 days ago. Nicole's airplane was at Nicole's sky, today. 18 boat were found at water. 4 boat were found at garage. Nihed's boat",
            "correct_answer": "highway",
            "prediction": "was at Nihed's water, today."
        },
        {
            "prompt_text": "Nicole's airplane was at Nicole's sky, 1 days ago. Fajjaaz's bench was at Fajjaaz's park, today. 14 bicycle were found at garage. 5 bicycle were found at highway. Nicole's bicycle",
            "correct_answer": "highway",
            "prediction": "Nicole's airplane was at Nicole's sky, 1 days ago. Fajjaa"
        },
        {
            "prompt_text": "Fajjaaz's bench was at Fajjaaz's park, 1 days ago. Hidde's motorcycle was at Hidde's garage, today. 22 bench were found at park. 7 bench were found at water. Fajjaaz's bench",
            "correct_answer": "park",
            "prediction": "1 bench at Fajjaaz's park"
        },
        {
            "prompt_text": "Hidde's motorcycle was at Hidde's garage, 1 days ago. Fajjaaz's bench was at Fajjaaz's water, today. 25 airplane were found at sky. 4 airplane were found at station. Nihed's airplane",
            "correct_answer": "sky",
            "prediction": "was at Nihed's sky, today."
        },
        {
            "prompt_text": "Fajjaaz's bench was at Fajjaaz's water, 1 days ago. Hidde's train was at Hidde's water, today. 14 train were found at station. 8 train were found at water. Fajjaaz's train",
            "correct_answer": "sky",
            "prediction": "was at Fajjaaz's water, 1 days ago. Hidde'"
        },
        {
            "prompt_text": "Hidde's train was at Hidde's water, 1 days ago. Taewoon's person was at Taewoon's university, today. 14 train were found at station. 9 train were found at water. Hidde's train",
            "correct_answer": "water",
            "prediction": "1 train was found at water."
        },
        {
            "prompt_text": "Taewoon's person was at Taewoon's university, 1 days ago. Taewoon's bicycle was at Taewoon's garage, today. 13 truck were found at highway. 5 truck were found at station. Nihed's truck",
            "correct_answer": "highway",
            "prediction": "was at Nihed's station, today."
        },
        {
            "prompt_text": "Taewoon's bicycle was at Taewoon's garage, today. 34 motorcycle were found at garage. 6 motorcycle were found at station. Hidde's motorcycle",
            "correct_answer": "garage",
            "prediction": "was found at station."
        },
        {
            "prompt_text": "Taewoon's bicycle was at Taewoon's garage, 1 days ago. Hidde's person was at Hidde's university, today. 26 person were found at university. 4 person were found at garage. Hidde's person",
            "correct_answer": "university",
            "prediction": "was at Hidde's university"
        },
        {
            "prompt_text": "Hidde's person was at Hidde's university, 1 days ago. Nihed's truck was at Nihed's garage, today. 22 bench were found at park. 9 bench were found at water. Fajjaaz's bench",
            "correct_answer": "water",
            "prediction": "was at Fajjaaz's park, today."
        },
        {
            "prompt_text": "Nihed's truck was at Nihed's garage, 1 days ago. Fajjaaz's train was at Fajjaaz's station, today. 25 airplane were found at sky. 4 airplane were found at station. Nihed's airplane",
            "correct_answer": "sky",
            "prediction": "was at Nihed's station, today."
        },
        {
            "prompt_text": "Fajjaaz's train was at Fajjaaz's station, 1 days ago. Hidde's bicycle was at Hidde's university, today. 34 motorcycle were found at garage. 6 motorcycle were found at station. Taewoon's motorcycle",
            "correct_answer": "garage",
            "prediction": "was at Taewoon's station, 1 days ago."
        },
        {
            "prompt_text": "Hidde's bicycle was at Hidde's university, 1 days ago. Fajjaaz's truck was at Fajjaaz's garage, today. 13 truck were found at highway. 7 truck were found at garage. Taewoon's truck",
            "correct_answer": "highway",
            "prediction": "was at Taewoon's garage, today."
        },
        {
            "prompt_text": "Fajjaaz's truck was at Fajjaaz's garage, 1 days ago. Nicole's truck was at Nicole's highway, today. 34 motorcycle were found at garage. 6 motorcycle were found at station. Fajjaaz's motorcycle",
            "correct_answer": "garage",
            "prediction": "was at Fajjaaz's garage, 1 days ago. Nicole's motorcycle"
        },
        {
            "prompt_text": "Nicole's truck was at Nicole's highway, 1 days ago. Taewoon's motorcycle was at Taewoon's park, today. 18 boat were found at water. 4 boat were found at garage. Nihed's boat",
            "correct_answer": "highway",
            "prediction": "was at Nihed's water, today."
        },
        {
            "prompt_text": "Taewoon's motorcycle was at Taewoon's park, 1 days ago. Fajjaaz's bench was at Fajjaaz's park, today. 23 bench were found at park. 9 bench were found at water. Fajjaaz's bench",
            "correct_answer": "park",
            "prediction": "was at Fajjaaz's park, today."
        },
        {
            "prompt_text": "Fajjaaz's bench was at Fajjaaz's park, 1 days ago. Nicole's bench was at Nicole's highway, today. 34 motorcycle were found at garage. 6 motorcycle were found at station. Taewoon's motorcycle",
            "correct_answer": "park",
            "prediction": "was at Taewoon's park, 1 days ago."
        },
        {
            "prompt_text": "Nicole's bench was at Nicole's highway, 1 days ago. Taewoon's boat was at Taewoon's water, today. 24 bench were found at park. 9 bench were found at water. Fajjaaz's bench",
            "correct_answer": "park",
            "prediction": "4 bench were found at water."
        },
        {
            "prompt_text": "Taewoon's boat was at Taewoon's water, 1 days ago. Nicole's bus was at Nicole's station, today. 20 boat were found at water. 4 boat were found at garage. Taewoon's boat",
            "correct_answer": "water",
            "prediction": "was at Taewoon's water, 1 days ago."
        },
        {
            "prompt_text": "Nicole's bus was at Nicole's station, 1 days ago. Nihed's bench was at Nihed's park, today. 25 bench were found at park. 9 bench were found at water. Fajjaaz's bench",
            "correct_answer": "park",
            "prediction": "3 bench were found at water."
        },
        {
            "prompt_text": "Nihed's bench was at Nihed's park, 1 days ago. Hidde's bicycle was at Hidde's garage, today. 26 bench were found at park. 9 bench were found at water. Fajjaaz's bench",
            "correct_answer": "park",
            "prediction": "was at Fajjaaz's park, 1 days ago."
        },
        {
            "prompt_text": "Hidde's bicycle was at Hidde's garage, 1 days ago. Nihed's boat was at Nihed's park, today. 19 bicycle were found at garage. 5 bicycle were found at university. Fajjaaz's bicycle",
            "correct_answer": "station",
            "prediction": "was at Fajjaaz's garage, 1 days ago."
        },
        {
            "prompt_text": "Nihed's boat was at Nihed's park, 1 days ago. Nicole's motorcycle was at Nicole's garage, today. 17 bus were found at station. 3 bus were found at park. Nicole's bus",
            "correct_answer": "station",
            "prediction": "was at Nicole's park, 1 days ago."
        },
        {
            "prompt_text": "Nicole's motorcycle was at Nicole's garage, 1 days ago. Taewoon's bus was at Taewoon's station, today. 36 motorcycle were found at garage. 6 motorcycle were found at station. Taewoon's motorcycle",
            "correct_answer": "park",
            "prediction": "was at Taewoon's station, today."
        },
        {
            "prompt_text": "Taewoon's bus was at Taewoon's station, 1 days ago. Hidde's bench was at Hidde's university, today. 26 bench were found at park. 9 bench were found at water. Fajjaaz's bench",
            "correct_answer": "park",
            "prediction": "was at Fajjaaz's university, today."
        },
        {
            "prompt_text": "Hidde's bench was at Hidde's university, 1 days ago. Nihed's car was at Nihed's garage, today. 27 person were found at university. 4 person were found at garage. Hidde's person",
            "correct_answer": "university",
            "prediction": "was found at university."
        },
        {
            "prompt_text": "Nihed's car was at Nihed's garage, 1 days ago. Hidde's airplane was at Hidde's sky, today. 19 bicycle were found at garage. 5 bicycle were found at university. Hidde's bicycle",
            "correct_answer": "garage",
            "prediction": "was at Hidde's sky, today."
        },
        {
            "prompt_text": "Hidde's airplane was at Hidde's sky, 1 days ago. Hidde's car was at Hidde's university, today. 27 airplane were found at sky. 4 airplane were found at station. Hidde's airplane",
            "correct_answer": "sky",
            "prediction": "was at Hidde's sky, 1 days ago. Hidde's car"
        },
        {
            "prompt_text": "Hidde's car was at Hidde's university, 1 days ago. Hidde's boat was at Hidde's water, today. 27 airplane were found at sky. 4 airplane were found at station. Hidde's airplane",
            "correct_answer": "sky",
            "prediction": "was at Hidde's sky, today."
        },
        {
            "prompt_text": "Hidde's boat was at Hidde's water, 1 days ago. Taewoon's airplane was at Taewoon's park, today. 13 car were found at garage. 7 car were found at university. Nihed's car",
            "correct_answer": "garage",
            "prediction": "was at Nihed's water, 1 days ago."
        },
        {
            "prompt_text": "Taewoon's airplane was at Taewoon's park, today. 26 bench were found at park. 9 bench were found at water. Fajjaaz's bench",
            "correct_answer": "park",
            "prediction": "was found at water."
        },
        {
            "prompt_text": "Taewoon's airplane was at Taewoon's park, 1 days ago. 36 motorcycle were found at garage. 6 motorcycle were found at station. Taewoon's motorcycle",
            "correct_answer": "park",
            "prediction": "was at Taewoon's park, 1 days ago."
        },
        {
            "prompt_text": "Taewoon's airplane was at Taewoon's sky, 1 days ago. Hidde's boat was at Hidde's water, today. 26 bench were found at park. 9 bench were found at water. Fajjaaz's bench",
            "correct_answer": "park",
            "prediction": "was at Fajjaaz's water, today."
        },
        {
            "prompt_text": "Hidde's boat was at Hidde's water, 1 days ago. Nicole's bus was at Nicole's park, today. 26 bench were found at park. 9 bench were found at water. Hidde's bench",
            "correct_answer": "university",
            "prediction": "was at Hidde's water, 1 days ago."
        },
        {
            "prompt_text": "Nicole's bus was at Nicole's park, 1 days ago. Nicole's motorcycle was at Nicole's garage, today. 19 bicycle were found at garage. 5 bicycle were found at university. Taewoon's bicycle",
            "correct_answer": "garage",
            "prediction": "was at Taewoon's garage, today."
        },
        {
            "prompt_text": "Nicole's motorcycle was at Nicole's garage, 1 days ago. Taewoon's bus was at Taewoon's station, today. 38 motorcycle were found at garage. 6 motorcycle were found at station. Taewoon's motorcycle",
            "correct_answer": "park",
            "prediction": "was at Taewoon's station, today."
        },
        {
            "prompt_text": "Taewoon's bus was at Taewoon's station, 1 days ago. Nihed's car was at Nihed's station, today. 26 bench were found at park. 9 bench were found at water. Fajjaaz's bench",
            "correct_answer": "park",
            "prediction": "was at Fajjaaz's station, today."
        },
        {
            "prompt_text": "Nihed's car was at Nihed's station, 1 days ago. Taewoon's truck was at Taewoon's highway, today. 13 car were found at garage. 7 car were found at university. Nicole's car",
            "correct_answer": "garage",
            "prediction": "was at Nicole's station, 1 days ago. Taewoon's truck was"
        },
        {
            "prompt_text": "Taewoon's truck was at Taewoon's highway, 1 days ago. Nihed's train was at Nihed's station, today. 17 train were found at station. 9 train were found at water. Nihed's train",
            "correct_answer": "station",
            "prediction": "was at Nihed's station, today."
        },
        {
            "prompt_text": "Nihed's train was at Nihed's station, 1 days ago. Nicole's car was at Nicole's garage, today. 29 airplane were found at sky. 4 airplane were found at station. Hidde's airplane",
            "correct_answer": "sky",
            "prediction": "was at Hidde's station, 1 days ago."
        },
        {
            "prompt_text": "Nicole's car was at Nicole's garage, 1 days ago. Nicole's motorcycle was at Nicole's garage, today. 24 boat were found at water. 5 boat were found at park. Nihed's boat",
            "correct_answer": "water",
            "prediction": "was at Nihed's garage, today."
        },
        {
            "prompt_text": "Nicole's motorcycle was at Nicole's garage, 1 days ago. Hidde's boat was at Hidde's sky, today. 29 airplane were found at sky. 4 airplane were found at park. Taewoon's airplane",
            "correct_answer": "sky",
            "prediction": "was at Taewoon's sky, today."
        },
        {
            "prompt_text": "Hidde's boat was at Hidde's sky, 1 days ago. Nicole's bus was at Nicole's garage, today. 26 bench were found at park. 9 bench were found at water. Fajjaaz's bench",
            "correct_answer": "park",
            "prediction": "was at Fajjaaz's water, today."
        },
        {
            "prompt_text": "Nicole's bus was at Nicole's garage, 1 days ago. Taewoon's motorcycle was at Taewoon's garage, today. 17 truck were found at highway. 8 truck were found at garage. Taewoon's truck",
            "correct_answer": "highway",
            "prediction": "was at Taewoon's garage, today."
        },
        {
            "prompt_text": "Taewoon's motorcycle was at Taewoon's garage, 1 days ago. Hidde's train was at Hidde's water, today. 17 truck were found at highway. 8 truck were found at garage. Taewoon's truck",
            "correct_answer": "highway",
            "prediction": "1 truck were found at garage."
        },
        {
            "prompt_text": "Hidde's train was at Hidde's water, 1 days ago. Hidde's bus was at Hidde's station, today. 18 train were found at station. 11 train were found at water. Nihed's train",
            "correct_answer": "station",
            "prediction": "1 train were found at water."
        },
        {
            "prompt_text": "Hidde's bus was at Hidde's station, 1 days ago. Nihed's boat was at Nihed's water, today. 26 bench were found at park. 9 bench were found at water. Nicole's bench",
            "correct_answer": "highway",
            "prediction": "was at Nicole's water, today."
        },
        {
            "prompt_text": "Nihed's boat was at Nihed's water, 1 days ago. Fajjaaz's person was at Fajjaaz's university, today. 17 truck were found at highway. 8 truck were found at garage. Nicole's truck",
            "correct_answer": "highway",
            "prediction": "was at Nicole's garage, today."
        },
        {
            "prompt_text": "Fajjaaz's person was at Fajjaaz's university, 1 days ago. Hidde's motorcycle was at Hidde's garage, today. 26 boat were found at water. 5 boat were found at park. Hidde's boat",
            "correct_answer": "sky",
            "prediction": "was at Hidde's garage, today."
        },
        {
            "prompt_text": "Hidde's motorcycle was at Hidde's garage, 1 days ago. Hidde's airplane was at Hidde's highway, today. 23 bus were found at station. 5 bus were found at park. Hidde's bus",
            "correct_answer": "station",
            "prediction": "was at Hidde's highway, today."
        },
        {
            "prompt_text": "Hidde's airplane was at Hidde's highway, 1 days ago. Hidde's train was at Hidde's station, today. 29 airplane were found at sky. 5 airplane were found at highway. Hidde's airplane",
            "correct_answer": "highway",
            "prediction": "1 airplane were found at highway."
        },
        {
            "prompt_text": "Hidde's train was at Hidde's station, 1 days ago. Taewoon's bench was at Taewoon's park, today. 44 motorcycle were found at garage. 6 motorcycle were found at station. Taewoon's motorcycle",
            "correct_answer": "garage",
            "prediction": "was at Taewoon's park, today."
        },
        {
            "prompt_text": "Taewoon's bench was at Taewoon's park, 1 days ago. Fajjaaz's train was at Fajjaaz's sky, today. 29 airplane were found at sky. 5 airplane were found at highway. Hidde's airplane",
            "correct_answer": "highway",
            "prediction": "was at Hidde's sky, today."
        },
        {
            "prompt_text": "Fajjaaz's train was at Fajjaaz's sky, 1 days ago. Taewoon's train was at Taewoon's station, today. 28 bench were found at park. 9 bench were found at water. Taewoon's bench",
            "correct_answer": "park",
            "prediction": "was at Taewoon's station, today."
        },
        {
            "prompt_text": "Taewoon's train was at Taewoon's station, 1 days ago. Hidde's person was at Hidde's university, today. 28 bench were found at park. 9 bench were found at water. Taewoon's bench",
            "correct_answer": "park",
            "prediction": "was at Taewoon's station, 1 days ago."
        },
        {
            "prompt_text": "Hidde's person was at Hidde's university, 1 days ago. Taewoon's bus was at Taewoon's park, today. 17 truck were found at highway. 8 truck were found at garage. Nihed's truck",
            "correct_answer": "garage",
            "prediction": "1 truck were found at highway."
        },
        {
            "prompt_text": "Taewoon's bus was at Taewoon's park, 1 days ago. Nicole's bus was at Nicole's station, today. 31 person were found at university. 4 person were found at garage. Hidde's person",
            "correct_answer": "university",
            "prediction": "was found at university."
        },
        {
            "prompt_text": "Nicole's bus was at Nicole's station, 1 days ago. Taewoon's bench was at Taewoon's park, today. 22 train were found at station. 11 train were found at water. Hidde's train",
            "correct_answer": "station",
            "prediction": "was at Hidde's station, 1 days ago."
        },
        {
            "prompt_text": "Taewoon's bench was at Taewoon's park, 1 days ago. Nicole's boat was at Nicole's water, today. 27 boat were found at water. 5 boat were found at park. Nihed's boat",
            "correct_answer": "water",
            "prediction": "was at Nihed's water, today."
        },
        {
            "prompt_text": "Nicole's boat was at Nicole's water, 1 days ago. Taewoon's motorcycle was at Taewoon's garage, today. 45 motorcycle were found at garage. 6 motorcycle were found at station. Nicole's motorcycle",
            "correct_answer": "garage",
            "prediction": "was at Nicole's garage, today."
        },
        {
            "prompt_text": "Taewoon's motorcycle was at Taewoon's garage, 1 days ago. Fajjaaz's truck was at Fajjaaz's water, today. 46 motorcycle were found at garage. 6 motorcycle were found at station. Nicole's motorcycle",
            "correct_answer": "garage",
            "prediction": "was at Nicole's garage, 1 days ago."
        },
        {
            "prompt_text": "Fajjaaz's truck was at Fajjaaz's water, 1 days ago. Taewoon's airplane was at Taewoon's sky, today. 28 boat were found at water. 5 boat were found at park. Nicole's boat",
            "correct_answer": "water",
            "prediction": "was at Nicole's water, today."
        },
        {
            "prompt_text": "Taewoon's airplane was at Taewoon's sky, 1 days ago. Nicole's motorcycle was at Nicole's garage, today. 31 person were found at university. 4 person were found at garage. Fajjaaz's person",
            "correct_answer": "university",
            "prediction": "was found at university."
        },
        {
            "prompt_text": "Nicole's motorcycle was at Nicole's garage, today. 25 bus were found at station. 7 bus were found at park. Nicole's bus",
            "correct_answer": "station",
            "prediction": "was at Nicole's garage, today."
        },
        {
            "prompt_text": "Nicole's motorcycle was at Nicole's garage, 1 days ago. Nihed's person was at Nihed's station, today. 49 motorcycle were found at garage. 6 motorcycle were found at station. Nicole's motorcycle",
            "correct_answer": "garage",
            "prediction": "Nicole's motorcycle was at Nicole's garage, 1 days ago. Nihed'"
        },
        {
            "prompt_text": "Nihed's person was at Nihed's station, 1 days ago. Taewoon's truck was at Taewoon's highway, today. 28 boat were found at water. 5 boat were found at park. Taewoon's boat",
            "correct_answer": "water",
            "prediction": "was at Taewoon's water, today."
        },
        {
            "prompt_text": "Taewoon's truck was at Taewoon's highway, 1 days ago. Taewoon's person was at Taewoon's university, today. 28 boat were found at water. 5 boat were found at park. Nihed's boat",
            "correct_answer": "water",
            "prediction": "was at Nihed's park, today."
        },
        {
            "prompt_text": "Taewoon's truck was at Taewoon's highway, today. 28 boat were found at water. 5 boat were found at park. Hidde's boat",
            "correct_answer": "sky",
            "prediction": "was at Taewoon's highway, today. 28 boat were found at water."
        },
        {
            "prompt_text": "Taewoon's truck was at Taewoon's highway, 1 days ago. Nihed's motorcycle was at Nihed's sky, today. 49 motorcycle were found at garage. 6 motorcycle were found at station. Nicole's motorcycle",
            "correct_answer": "garage",
            "prediction": "was at Nicole's sky, today."
        },
        {
            "prompt_text": "Nihed's motorcycle was at Nihed's sky, 1 days ago. Nihed's airplane was at Nihed's sky, today. 32 airplane were found at sky. 5 airplane were found at highway. Taewoon's airplane",
            "correct_answer": "sky",
            "prediction": "was at Taewoon's sky, today."
        },
        {
            "prompt_text": "Nihed's airplane was at Nihed's sky, 1 days ago. 28 boat were found at water. 5 boat were found at park. Nicole's boat",
            "correct_answer": "water",
            "prediction": "was at Nicole's sky, 1 days ago. 28 boat were found at water. 5"
        },
        {
            "prompt_text": "Nihed's airplane was at Nihed's highway, 1 days ago. Nihed's boat was at Nihed's water, today. 29 boat were found at water. 5 boat were found at park. Nicole's boat",
            "correct_answer": "water",
            "prediction": "was at Nicole's water, today."
        },
        {
            "prompt_text": "Nihed's airplane was at Nihed's highway, today. 15 car were found at garage. 7 car were found at university. Nihed's car",
            "correct_answer": "station",
            "prediction": "was found at university."
        },
        {
            "prompt_text": "Nihed's airplane was at Nihed's highway, 1 days ago. Nicole's truck was at Nicole's highway, today. 19 bicycle were found at garage. 5 bicycle were found at university. Hidde's bicycle",
            "correct_answer": "garage",
            "prediction": "was at Hidde's highway, today."
        },
        {
            "prompt_text": "Nicole's truck was at Nicole's highway, 1 days ago. Taewoon's airplane was at Taewoon's sky, today. 23 truck were found at highway. 8 truck were found at garage. Nicole's truck",
            "correct_answer": "highway",
            "prediction": "Nicole's highway"
        },
        {
            "prompt_text": "Taewoon's airplane was at Taewoon's sky, 1 days ago. Hidde's boat was at Hidde's water, today. 19 bicycle were found at garage. 5 bicycle were found at university. Hidde's bicycle",
            "correct_answer": "garage",
            "prediction": "was at Hidde's water, today."
        },
        {
            "prompt_text": "Hidde's boat was at Hidde's water, 1 days ago. Nihed's bus was at Nihed's station, today. 22 train were found at station. 11 train were found at water. Taewoon's train",
            "correct_answer": "station",
            "prediction": "was at Taewoon's station, today."
        },
        {
            "prompt_text": "Nihed's bus was at Nihed's station, 1 days ago. Nicole's motorcycle was at Nicole's garage, today. 23 truck were found at highway. 8 truck were found at garage. Hidde's truck",
            "correct_answer": "station",
            "prediction": "was at Hidde's garage, today."
        },
        {
            "prompt_text": "Nihed's bus was at Nihed's station, today. 32 person were found at university. 4 person were found at garage. Taewoon's person",
            "correct_answer": "university",
            "prediction": "4 person were found at garage."
        },
        {
            "prompt_text": "Nihed's bus was at Nihed's station, 1 days ago. Fajjaaz's person was at Fajjaaz's university, today. 33 person were found at university. 4 person were found at garage. Fajjaaz's person",
            "correct_answer": "university",
            "prediction": "was at Fajjaaz's university"
        },
        {
            "prompt_text": "Fajjaaz's person was at Fajjaaz's university, today. 22 train were found at station. 11 train were found at water. Fajjaaz's train",
            "correct_answer": "sky",
            "prediction": "was at station."
        },
        {
            "prompt_text": "Fajjaaz's person was at Fajjaaz's university, 1 days ago. Taewoon's boat was at Taewoon's water, today. 22 train were found at station. 11 train were found at water. Fajjaaz's train",
            "correct_answer": "sky",
            "prediction": "was at Fajjaaz's university, 1 days ago. Taewoon"
        },
        {
            "prompt_text": "Taewoon's boat was at Taewoon's water, today. 35 person were found at university. 4 person were found at garage. Fajjaaz's person",
            "correct_answer": "university",
            "prediction": "5 person were found at garage."
        },
        {
            "prompt_text": "Taewoon's boat was at Taewoon's water, 1 days ago. Nicole's bicycle was at Nicole's garage, today. 30 bench were found at park. 9 bench were found at water. Taewoon's bench",
            "correct_answer": "park",
            "prediction": "was at Taewoon's water, 1 days ago."
        },
        {
            "prompt_text": "Nicole's bicycle was at Nicole's garage, 1 days ago. Hidde's truck was at Hidde's station, today. 15 car were found at garage. 7 car were found at university. Nihed's car",
            "correct_answer": "station",
            "prediction": "was at Nihed's station, today."
        },
        {
            "prompt_text": "Hidde's truck was at Hidde's station, 1 days ago. Taewoon's motorcycle was at Taewoon's highway, today. 29 bus were found at station. 7 bus were found at park. Nihed's bus",
            "correct_answer": "station",
            "prediction": "was at Nihed's park, today."
        },
        {
            "prompt_text": "Taewoon's motorcycle was at Taewoon's highway, 1 days ago. Nicole's person was at Nicole's garage, today. 22 train were found at station. 11 train were found at water. Taewoon's train",
            "correct_answer": "station",
            "prediction": "was at Taewoon's station, today."
        },
        {
            "prompt_text": "Nicole's person was at Nicole's garage, 1 days ago. Taewoon's boat was at Taewoon's park, today. 35 airplane were found at sky. 9 airplane were found at highway. Taewoon's airplane",
            "correct_answer": "sky",
            "prediction": "was at Taewoon's park, today."
        },
        {
            "prompt_text": "Taewoon's boat was at Taewoon's park, 1 days ago. Nicole's car was at Nicole's station, today. 23 truck were found at highway. 8 truck were found at garage. Taewoon's truck",
            "correct_answer": "highway",
            "prediction": "was at Taewoon's garage, today."
        },
        {
            "prompt_text": "Nicole's car was at Nicole's station, 1 days ago. Hidde's person was at Hidde's university, today. 50 motorcycle were found at garage. 6 motorcycle were found at station. Hidde's motorcycle",
            "correct_answer": "garage",
            "prediction": "was at Hidde's university, today."
        },
        {
            "prompt_text": "Hidde's person was at Hidde's university, 1 days ago. Fajjaaz's boat was at Fajjaaz's water, today. 37 person were found at university. 6 person were found at garage. Hidde's person",
            "correct_answer": "university",
            "prediction": "1 days ago"
        },
        {
            "prompt_text": "Fajjaaz's boat was at Fajjaaz's water, 1 days ago. Taewoon's bicycle was at Taewoon's garage, today. 23 truck were found at highway. 8 truck were found at garage. Taewoon's truck",
            "correct_answer": "highway",
            "prediction": "was at Taewoon's garage, today."
        }
    ],
    "test": [
        {
            "prompt_text": "Taewoon's airplane was at Taewoon's highway, today. 35 airplane were found at sky. 10 airplane were found at highway. Taewoon's airplane",
            "correct_answer": "highway",
            "prediction": "was at Taewoon's highway, today."
        },
        {
            "prompt_text": "Taewoon's airplane was at Taewoon's highway, 1 days ago. Nihed's bench was at Nihed's station, today. 30 bench were found at park. 9 bench were found at water. Nihed's bench",
            "correct_answer": "station",
            "prediction": "30 bench were found at park. 9 bench were found at water."
        },
        {
            "prompt_text": "Nihed's bench was at Nihed's station, 1 days ago. Taewoon's truck was at Taewoon's station, today. 30 bench were found at park. 9 bench were found at water. Nihed's bench",
            "correct_answer": "station",
            "prediction": "1 bench at Nihed's station"
        },
        {
            "prompt_text": "Taewoon's truck was at Taewoon's station, 1 days ago. Hidde's airplane was at Hidde's sky, today. 36 airplane were found at sky. 11 airplane were found at highway. Taewoon's airplane",
            "correct_answer": "highway",
            "prediction": "was at Taewoon's sky, today."
        },
        {
            "prompt_text": "Hidde's airplane was at Hidde's sky, 1 days ago. Taewoon's train was at Taewoon's station, today. 37 airplane were found at sky. 11 airplane were found at highway. Hidde's airplane",
            "correct_answer": "sky",
            "prediction": "1 days ago"
        },
        {
            "prompt_text": "Taewoon's train was at Taewoon's station, 1 days ago. Nihed's train was at Nihed's sky, today. 30 bench were found at park. 9 bench were found at water. Nihed's bench",
            "correct_answer": "station",
            "prediction": "was at Nihed's sky, today."
        },
        {
            "prompt_text": "Nihed's train was at Nihed's sky, 1 days ago. Hidde's airplane was at Hidde's water, today. 24 train were found at station. 11 train were found at water. Taewoon's train",
            "correct_answer": "station",
            "prediction": "1 train were found at station. 11 train were found at water."
        },
        {
            "prompt_text": "Hidde's airplane was at Hidde's water, 1 days ago. Fajjaaz's bench was at Fajjaaz's water, today. 37 airplane were found at sky. 11 airplane were found at highway. Hidde's airplane",
            "correct_answer": "water",
            "prediction": "Hidde's airplane was at Hidde's water, 1 days ago."
        },
        {
            "prompt_text": "Fajjaaz's bench was at Fajjaaz's water, 1 days ago. Nicole's airplane was at Nicole's sky, today. 24 train were found at station. 11 train were found at water. Nihed's train",
            "correct_answer": "sky",
            "prediction": "was at Nihed's water, today."
        },
        {
            "prompt_text": "Nicole's airplane was at Nicole's sky, 1 days ago. Nihed's person was at Nihed's university, today. 39 airplane were found at sky. 11 airplane were found at highway. Nicole's airplane",
            "correct_answer": "sky",
            "prediction": "Nicole's airplane was at Nicole's sky, 1 days ago. Nihed'"
        },
        {
            "prompt_text": "Nihed's person was at Nihed's university, today. 39 person were found at university. 6 person were found at garage. Nihed's person",
            "correct_answer": "university",
            "prediction": "39"
        },
        {
            "prompt_text": "Nihed's person was at Nihed's university, 1 days ago. Nicole's bench was at Nicole's park, today. 39 airplane were found at sky. 11 airplane were found at highway. Hidde's airplane",
            "correct_answer": "sky",
            "prediction": "was at Hidde's airport, today."
        },
        {
            "prompt_text": "Nicole's bench was at Nicole's park, 1 days ago. Nihed's airplane was at Nihed's station, today. 39 airplane were found at sky. 11 airplane were found at highway. Nicole's airplane",
            "correct_answer": "sky",
            "prediction": "Nicole's bench was at Nicole's park, 1 days ago. Nihed'"
        },
        {
            "prompt_text": "Nihed's airplane was at Nihed's station, today. 39 airplane were found at sky. 11 airplane were found at highway. Nihed's airplane",
            "correct_answer": "station",
            "prediction": "was at Nihed's station, today."
        },
        {
            "prompt_text": "Nihed's airplane was at Nihed's station, 1 days ago. Nihed's motorcycle was at Nihed's highway, today. 24 train were found at station. 11 train were found at water. Nihed's train",
            "correct_answer": "sky",
            "prediction": "was at Nihed's station, 1 days ago. Nihed's motorcycle"
        },
        {
            "prompt_text": "Nihed's motorcycle was at Nihed's highway, 1 days ago. Nicole's bench was at Nicole's water, today. 24 train were found at station. 11 train were found at water. Nihed's train",
            "correct_answer": "sky",
            "prediction": "was at Nihed's highway, 1 days ago. Nicole's bench was at"
        },
        {
            "prompt_text": "Nicole's bench was at Nicole's water, 1 days ago. Taewoon's train was at Taewoon's station, today. 32 bench were found at park. 13 bench were found at water. Nicole's bench",
            "correct_answer": "water",
            "prediction": "1 bench at Nicole's water"
        },
        {
            "prompt_text": "Taewoon's train was at Taewoon's station, 1 days ago. Hidde's motorcycle was at Hidde's garage, today. 26 train were found at station. 11 train were found at water. Taewoon's train",
            "correct_answer": "station",
            "prediction": "1 train were found at water."
        },
        {
            "prompt_text": "Hidde's motorcycle was at Hidde's garage, 1 days ago. Taewoon's motorcycle was at Taewoon's station, today. 39 airplane were found at sky. 11 airplane were found at highway. Hidde's airplane",
            "correct_answer": "sky",
            "prediction": "was at Hidde's garage, 1 days ago. Taewoon's"
        },
        {
            "prompt_text": "Taewoon's motorcycle was at Taewoon's station, 1 days ago. Taewoon's truck was at Taewoon's park, today. 52 motorcycle were found at garage. 8 motorcycle were found at station. Nihed's motorcycle",
            "correct_answer": "highway",
            "prediction": "was at Nihed's station, 1 days ago."
        },
        {
            "prompt_text": "Taewoon's truck was at Taewoon's park, 1 days ago. Nihed's bicycle was at Nihed's highway, today. 52 motorcycle were found at garage. 8 motorcycle were found at station. Taewoon's motorcycle",
            "correct_answer": "station",
            "prediction": "was at Taewoon's park, 1 days ago. Nihed's"
        },
        {
            "prompt_text": "Nihed's bicycle was at Nihed's highway, 1 days ago. Hidde's bus was at Hidde's station, today. 30 bus were found at station. 7 bus were found at park. Hidde's bus",
            "correct_answer": "station",
            "prediction": "was at Hidde's station, today."
        },
        {
            "prompt_text": "Hidde's bus was at Hidde's station, 1 days ago. Fajjaaz's motorcycle was at Fajjaaz's garage, today. 39 airplane were found at sky. 11 airplane were found at highway. Nicole's airplane",
            "correct_answer": "sky",
            "prediction": "was at Nicole's airport, today."
        },
        {
            "prompt_text": "Fajjaaz's motorcycle was at Fajjaaz's garage, 1 days ago. Fajjaaz's airplane was at Fajjaaz's station, today. 54 motorcycle were found at garage. 8 motorcycle were found at station. Fajjaaz's motorcycle",
            "correct_answer": "garage",
            "prediction": "was at Fajjaaz's garage, 1 days ago. Fajjaa"
        },
        {
            "prompt_text": "Fajjaaz's airplane was at Fajjaaz's station, 1 days ago. Hidde's train was at Hidde's park, today. 39 airplane were found at sky. 11 airplane were found at highway. Nihed's airplane",
            "correct_answer": "station",
            "prediction": "was at Nihed's station, 1 days ago."
        },
        {
            "prompt_text": "Hidde's train was at Hidde's park, 1 days ago. Nihed's motorcycle was at Nihed's garage, today. 55 motorcycle were found at garage. 8 motorcycle were found at station. Fajjaaz's motorcycle",
            "correct_answer": "garage",
            "prediction": "was at Fajjaaz's garage, today."
        },
        {
            "prompt_text": "Nihed's motorcycle was at Nihed's garage, 1 days ago. Taewoon's bench was at Taewoon's park, today. 39 airplane were found at sky. 11 airplane were found at highway. Nihed's airplane",
            "correct_answer": "station",
            "prediction": "was at Nihed's airport, 1 days ago."
        },
        {
            "prompt_text": "Taewoon's bench was at Taewoon's park, 1 days ago. Nicole's bicycle was at Nicole's garage, today. 56 motorcycle were found at garage. 8 motorcycle were found at station. Hidde's motorcycle",
            "correct_answer": "garage",
            "prediction": "was at Hidde's garage, today."
        },
        {
            "prompt_text": "Nicole's bicycle was at Nicole's garage, 1 days ago. Hidde's bicycle was at Hidde's highway, today. 40 person were found at university. 6 person were found at garage. Nihed's person",
            "correct_answer": "university",
            "prediction": "was found at garage."
        },
        {
            "prompt_text": "Hidde's bicycle was at Hidde's highway, 1 days ago. Nihed's bus was at Nihed's park, today. 56 motorcycle were found at garage. 8 motorcycle were found at station. Fajjaaz's motorcycle",
            "correct_answer": "garage",
            "prediction": "was at Fajjaaz's highway, 1 days ago."
        },
        {
            "prompt_text": "Nihed's bus was at Nihed's park, 1 days ago. Nihed's car was at Nihed's garage, today. 24 bicycle were found at garage. 9 bicycle were found at highway. Nicole's bicycle",
            "correct_answer": "garage",
            "prediction": "was at Nicole's park, 1 days ago. Nihed's car was at"
        },
        {
            "prompt_text": "Nihed's car was at Nihed's garage, 1 days ago. Taewoon's person was at Taewoon's university, today. 24 bicycle were found at garage. 9 bicycle were found at highway. Nihed's bicycle",
            "correct_answer": "highway",
            "prediction": "was found at highway."
        },
        {
            "prompt_text": "Nihed's car was at Nihed's garage, today. 26 train were found at station. 11 train were found at water. Hidde's train",
            "correct_answer": "park",
            "prediction": "was at Hidde's garage, today."
        },
        {
            "prompt_text": "Nihed's car was at Nihed's garage, 1 days ago. Fajjaaz's train was at Fajjaaz's station, today. 39 airplane were found at sky. 11 airplane were found at highway. Nihed's airplane",
            "correct_answer": "station",
            "prediction": "was at Nihed's airport, today."
        },
        {
            "prompt_text": "Fajjaaz's train was at Fajjaaz's station, 1 days ago. Nihed's truck was at Nihed's garage, today. 41 person were found at university. 6 person were found at garage. Taewoon's person",
            "correct_answer": "university",
            "prediction": "was found at university."
        },
        {
            "prompt_text": "Nihed's truck was at Nihed's garage, 1 days ago. Hidde's bench was at Hidde's park, today. 31 bus were found at station. 9 bus were found at park. Nihed's bus",
            "correct_answer": "park",
            "prediction": "was at Nihed's garage, 1 days ago. Hidde's bench"
        },
        {
            "prompt_text": "Hidde's bench was at Hidde's park, 1 days ago. Taewoon's train was at Taewoon's station, today. 29 train were found at station. 11 train were found at water. Taewoon's train",
            "correct_answer": "station",
            "prediction": "Hidde's bench was at Hidde's park, 1 days ago."
        },
        {
            "prompt_text": "Taewoon's train was at Taewoon's station, 1 days ago. Taewoon's motorcycle was at Taewoon's garage, today. 24 bicycle were found at garage. 9 bicycle were found at highway. Hidde's bicycle",
            "correct_answer": "highway",
            "prediction": "was at Hidde's garage, today."
        },
        {
            "prompt_text": "Taewoon's motorcycle was at Taewoon's garage, 1 days ago. Nicole's bus was at Nicole's station, today. 36 bench were found at park. 13 bench were found at water. Taewoon's bench",
            "correct_answer": "park",
            "prediction": "was at Taewoon's garage, 1 days ago."
        },
        {
            "prompt_text": "Nicole's bus was at Nicole's station, 1 days ago. Taewoon's car was at Taewoon's university, today. 36 bench were found at park. 13 bench were found at water. Taewoon's bench",
            "correct_answer": "park",
            "prediction": "was at Taewoon's university, today."
        },
        {
            "prompt_text": "Taewoon's car was at Taewoon's university, 1 days ago. Nicole's boat was at Nicole's highway, today. 36 bench were found at park. 13 bench were found at water. Taewoon's bench",
            "correct_answer": "park",
            "prediction": "was at Taewoon's university, 1 days ago."
        },
        {
            "prompt_text": "Nicole's boat was at Nicole's highway, 1 days ago. Fajjaaz's motorcycle was at Fajjaaz's park, today. 36 bench were found at park. 13 bench were found at water. Hidde's bench",
            "correct_answer": "park",
            "prediction": "was at Hidde's park, today."
        },
        {
            "prompt_text": "Fajjaaz's motorcycle was at Fajjaaz's park, 1 days ago. Hidde's bicycle was at Hidde's water, today. 30 train were found at station. 11 train were found at water. Hidde's train",
            "correct_answer": "park",
            "prediction": "was at Hidde's water, today."
        },
        {
            "prompt_text": "Hidde's bicycle was at Hidde's water, 1 days ago. Taewoon's bicycle was at Taewoon's garage, today. 41 person were found at university. 6 person were found at garage. Taewoon's person",
            "correct_answer": "university",
            "prediction": "was found at garage."
        },
        {
            "prompt_text": "Taewoon's bicycle was at Taewoon's garage, 1 days ago. Nihed's train was at Nihed's water, today. 26 bicycle were found at garage. 9 bicycle were found at highway. Hidde's bicycle",
            "correct_answer": "water",
            "prediction": "was at Hidde's garage, 1 days ago."
        },
        {
            "prompt_text": "Nihed's train was at Nihed's water, 1 days ago. Taewoon's train was at Taewoon's station, today. 19 car were found at garage. 9 car were found at university. Nihed's car",
            "correct_answer": "garage",
            "prediction": "1 car were found at university."
        },
        {
            "prompt_text": "Taewoon's train was at Taewoon's station, 1 days ago. Fajjaaz's bus was at Fajjaaz's station, today. 32 train were found at station. 13 train were found at water. Fajjaaz's train",
            "correct_answer": "station",
            "prediction": "was at Fajjaaz's station, today. 32 train were found at station"
        },
        {
            "prompt_text": "Fajjaaz's bus was at Fajjaaz's station, 1 days ago. Taewoon's motorcycle was at Taewoon's station, today. 35 bus were found at station. 9 bus were found at park. Nicole's bus",
            "correct_answer": "station",
            "prediction": "was at Nicole's station, 1 days ago."
        },
        {
            "prompt_text": "Taewoon's motorcycle was at Taewoon's station, 1 days ago. Taewoon's bench was at Taewoon's sky, today. 32 train were found at station. 13 train were found at water. Taewoon's train",
            "correct_answer": "station",
            "prediction": "was at Taewoon's station, 1 days ago. Taewoon'"
        },
        {
            "prompt_text": "Taewoon's bench was at Taewoon's sky, 1 days ago. Taewoon's bus was at Taewoon's highway, today. 32 train were found at station. 13 train were found at water. Nihed's train",
            "correct_answer": "water",
            "prediction": "was at Nihed's station, today."
        },
        {
            "prompt_text": "Taewoon's bus was at Taewoon's highway, 1 days ago. Hidde's train was at Hidde's station, today. 23 truck were found at highway. 10 truck were found at garage. Nihed's truck",
            "correct_answer": "garage",
            "prediction": "1 truck was found at garage."
        },
        {
            "prompt_text": "Hidde's train was at Hidde's station, 1 days ago. Nihed's bench was at Nihed's park, today. 35 bus were found at station. 9 bus were found at park. Hidde's bus",
            "correct_answer": "station",
            "prediction": "1 bus were found at park."
        },
        {
            "prompt_text": "Nihed's bench was at Nihed's park, today. 41 person were found at university. 6 person were found at garage. Taewoon's person",
            "correct_answer": "university",
            "prediction": "4 person were found at university."
        },
        {
            "prompt_text": "Nihed's bench was at Nihed's park, 1 days ago. 34 train were found at station. 13 train were found at water. Taewoon's train",
            "correct_answer": "station",
            "prediction": "was at Taewoon's park, 1 days ago."
        },
        {
            "prompt_text": "Fajjaaz's bench was at Fajjaaz's highway, today. 41 person were found at university. 6 person were found at garage. Fajjaaz's person",
            "correct_answer": "university",
            "prediction": "4 person were found at university."
        },
        {
            "prompt_text": "Fajjaaz's bench was at Fajjaaz's highway, 1 days ago. Nihed's airplane was at Nihed's sky, today. 26 bicycle were found at garage. 9 bicycle were found at highway. Nicole's bicycle",
            "correct_answer": "garage",
            "prediction": "was at Nicole's highway, today."
        },
        {
            "prompt_text": "Nihed's airplane was at Nihed's sky, 1 days ago. Hidde's airplane was at Hidde's station, today. 35 bus were found at station. 9 bus were found at park. Nicole's bus",
            "correct_answer": "station",
            "prediction": "was at Nicole's station, today."
        },
        {
            "prompt_text": "Hidde's airplane was at Hidde's station, 1 days ago. Nicole's motorcycle was at Nicole's university, today. 34 train were found at station. 13 train were found at water. Taewoon's train",
            "correct_answer": "station",
            "prediction": "was at Taewoon's station, 1 days ago."
        },
        {
            "prompt_text": "Nicole's motorcycle was at Nicole's university, 1 days ago. Taewoon's truck was at Taewoon's university, today. 34 train were found at station. 13 train were found at water. Nicole's train",
            "correct_answer": "station",
            "prediction": "was at Nicole's university, 1 days ago. Taewoon's truck was"
        },
        {
            "prompt_text": "Taewoon's truck was at Taewoon's university, 1 days ago. Taewoon's person was at Taewoon's highway, today. 35 bus were found at station. 9 bus were found at park. Fajjaaz's bus",
            "correct_answer": "station",
            "prediction": "was at Fajjaaz's park."
        },
        {
            "prompt_text": "Taewoon's person was at Taewoon's highway, 1 days ago. Hidde's person was at Hidde's water, today. 58 motorcycle were found at garage. 10 motorcycle were found at station. Taewoon's motorcycle",
            "correct_answer": "station",
            "prediction": "1 days ago"
        },
        {
            "prompt_text": "Hidde's person was at Hidde's water, 1 days ago. Nihed's truck was at Nihed's garage, today. 40 bench were found at park. 13 bench were found at water. Taewoon's bench",
            "correct_answer": "sky",
            "prediction": "was at Taewoon's water, today."
        },
        {
            "prompt_text": "Nihed's truck was at Nihed's garage, 1 days ago. Nicole's person was at Nicole's university, today. 42 person were found at university. 6 person were found at garage. Nicole's person",
            "correct_answer": "university",
            "prediction": "was at Nicole's university"
        },
        {
            "prompt_text": "Nicole's person was at Nicole's university, 1 days ago. Nihed's train was at Nihed's station, today. 58 motorcycle were found at garage. 10 motorcycle were found at station. Fajjaaz's motorcycle",
            "correct_answer": "park",
            "prediction": "was at Fajjaaz's station, today."
        },
        {
            "prompt_text": "Nihed's train was at Nihed's station, 1 days ago. Hidde's car was at Hidde's garage, today. 40 bench were found at park. 13 bench were found at water. Nicole's bench",
            "correct_answer": "water",
            "prediction": "was at Nicole's park, today."
        },
        {
            "prompt_text": "Hidde's car was at Hidde's garage, 1 days ago. Taewoon's train was at Taewoon's water, today. 41 airplane were found at sky. 11 airplane were found at station. Fajjaaz's airplane",
            "correct_answer": "station",
            "prediction": "was at Fajjaaz's sky, today."
        },
        {
            "prompt_text": "Taewoon's train was at Taewoon's water, 1 days ago. Fajjaaz's bench was at Fajjaaz's garage, today. 41 airplane were found at sky. 11 airplane were found at station. Hidde's airplane",
            "correct_answer": "station",
            "prediction": "was at Hidde's station, today."
        },
        {
            "prompt_text": "Fajjaaz's bench was at Fajjaaz's garage, 1 days ago. Fajjaaz's motorcycle was at Fajjaaz's garage, today. 40 bench were found at park. 13 bench were found at water. Taewoon's bench",
            "correct_answer": "sky",
            "prediction": "was at Taewoon's garage, 1 days ago."
        },
        {
            "prompt_text": "Fajjaaz's motorcycle was at Fajjaaz's garage, 1 days ago. Nihed's bus was at Nihed's sky, today. 35 bus were found at station. 9 bus were found at park. Hidde's bus",
            "correct_answer": "station",
            "prediction": "was at Hidde's sky, today."
        },
        {
            "prompt_text": "Nihed's bus was at Nihed's sky, 1 days ago. Nicole's airplane was at Nicole's sky, today. 60 motorcycle were found at garage. 10 motorcycle were found at station. Taewoon's motorcycle",
            "correct_answer": "station",
            "prediction": "was at Taewoon's sky, today."
        },
        {
            "prompt_text": "Nicole's airplane was at Nicole's sky, 1 days ago. Taewoon's train was at Taewoon's station, today. 35 bus were found at station. 9 bus were found at park. Taewoon's bus",
            "correct_answer": "highway",
            "prediction": "was at Taewoon's station, today."
        },
        {
            "prompt_text": "Taewoon's train was at Taewoon's station, 1 days ago. Nicole's bench was at Nicole's park, today. 41 bench were found at park. 13 bench were found at water. Fajjaaz's bench",
            "correct_answer": "garage",
            "prediction": "was at Fajjaaz's park, today."
        },
        {
            "prompt_text": "Taewoon's train was at Taewoon's station, today. 23 truck were found at highway. 12 truck were found at garage. Nihed's truck",
            "correct_answer": "garage",
            "prediction": "was found at garage."
        },
        {
            "prompt_text": "Taewoon's train was at Taewoon's station, 1 days ago. Taewoon's motorcycle was at Taewoon's garage, today. 41 bench were found at park. 13 bench were found at water. Nihed's bench",
            "correct_answer": "park",
            "prediction": "was at Nihed's station, 1 days ago."
        },
        {
            "prompt_text": "Taewoon's motorcycle was at Taewoon's garage, 1 days ago. Hidde's bench was at Hidde's park, today. 42 bench were found at park. 13 bench were found at water. Nicole's bench",
            "correct_answer": "park",
            "prediction": "was at Nicole's park, today. 42 bench were found at park. 13 bench were"
        },
        {
            "prompt_text": "Hidde's bench was at Hidde's park, 1 days ago. Hidde's person was at Hidde's university, today. 35 bus were found at station. 9 bus were found at park. Taewoon's bus",
            "correct_answer": "highway",
            "prediction": "was at Taewoon's university, today."
        },
        {
            "prompt_text": "Hidde's person was at Hidde's university, 1 days ago. Taewoon's truck was at Taewoon's highway, today. 21 car were found at garage. 9 car were found at university. Taewoon's car",
            "correct_answer": "university",
            "prediction": "was at Taewoon's highway, today."
        },
        {
            "prompt_text": "Taewoon's truck was at Taewoon's highway, 1 days ago. Fajjaaz's car was at Fajjaaz's garage, today. 22 car were found at garage. 9 car were found at university. Hidde's car",
            "correct_answer": "garage",
            "prediction": "was at Hidde's garage, today."
        },
        {
            "prompt_text": "Fajjaaz's car was at Fajjaaz's garage, 1 days ago. Taewoon's person was at Taewoon's water, today. 43 bench were found at park. 13 bench were found at water. Hidde's bench",
            "correct_answer": "park",
            "prediction": "was at Hidde's water, today."
        },
        {
            "prompt_text": "Taewoon's person was at Taewoon's water, 1 days ago. Hidde's airplane was at Hidde's garage, today. 43 bench were found at park. 13 bench were found at water. Nihed's bench",
            "correct_answer": "park",
            "prediction": "was at Nihed's water, today."
        },
        {
            "prompt_text": "Hidde's airplane was at Hidde's garage, 1 days ago. Fajjaaz's car was at Fajjaaz's garage, today. 62 motorcycle were found at garage. 10 motorcycle were found at station. Fajjaaz's motorcycle",
            "correct_answer": "garage",
            "prediction": "was at Fajjaaz's garage, today."
        },
        {
            "prompt_text": "Fajjaaz's car was at Fajjaaz's garage, 1 days ago. Hidde's motorcycle was at Hidde's garage, today. 43 airplane were found at sky. 11 airplane were found at station. Nicole's airplane",
            "correct_answer": "sky",
            "prediction": "was at Nicole's garage, today."
        },
        {
            "prompt_text": "Hidde's motorcycle was at Hidde's garage, 1 days ago. Hidde's bus was at Hidde's station, today. 36 bus were found at station. 9 bus were found at park. Nicole's bus",
            "correct_answer": "station",
            "prediction": "was at Nicole's station, today."
        },
        {
            "prompt_text": "Hidde's bus was at Hidde's station, 1 days ago. Nicole's bicycle was at Nicole's garage, today. 64 motorcycle were found at garage. 10 motorcycle were found at station. Nicole's motorcycle",
            "correct_answer": "university",
            "prediction": "was at Nicole's garage, today."
        },
        {
            "prompt_text": "Nicole's bicycle was at Nicole's garage, 1 days ago. Nicole's boat was at Nicole's garage, today. 25 truck were found at highway. 12 truck were found at garage. Nihed's truck",
            "correct_answer": "garage",
            "prediction": "was at Nihed's garage, today."
        },
        {
            "prompt_text": "Nicole's boat was at Nicole's garage, 1 days ago. Nihed's truck was at Nihed's water, today. 36 boat were found at water. 7 boat were found at park. Nicole's boat",
            "correct_answer": "garage",
            "prediction": "Nicole's boat was at Nicole's garage, 1 days ago. Nihed'"
        },
        {
            "prompt_text": "Nihed's truck was at Nihed's water, 1 days ago. Fajjaaz's bench was at Fajjaaz's park, today. 37 bus were found at station. 9 bus were found at park. Taewoon's bus",
            "correct_answer": "highway",
            "prediction": "was at Taewoon's park, today."
        },
        {
            "prompt_text": "Fajjaaz's bench was at Fajjaaz's park, 1 days ago. Taewoon's car was at Taewoon's garage, today. 26 car were found at garage. 9 car were found at university. Fajjaaz's car",
            "correct_answer": "garage",
            "prediction": "was at Fajjaaz's park, 1 days ago. Taewoon"
        },
        {
            "prompt_text": "Taewoon's car was at Taewoon's garage, 1 days ago. Nihed's bench was at Nihed's water, today. 40 train were found at station. 15 train were found at water. Nicole's train",
            "correct_answer": "station",
            "prediction": "was at Nicole's station, 1 days ago."
        },
        {
            "prompt_text": "Nihed's bench was at Nihed's water, 1 days ago. Nicole's person was at Nicole's university, today. 28 bicycle were found at garage. 9 bicycle were found at highway. Hidde's bicycle",
            "correct_answer": "water",
            "prediction": "was at Hidde's water, 1 days ago."
        },
        {
            "prompt_text": "Nicole's person was at Nicole's university, 1 days ago. Fajjaaz's bicycle was at Fajjaaz's university, today. 47 person were found at university. 7 person were found at water. Nicole's person",
            "correct_answer": "university",
            "prediction": "Nicole's person was at Nicole's university, 1 days ago. Fajjaa"
        },
        {
            "prompt_text": "Fajjaaz's bicycle was at Fajjaaz's university, 1 days ago. Fajjaaz's truck was at Fajjaaz's highway, today. 27 car were found at garage. 9 car were found at university. Nihed's car",
            "correct_answer": "garage",
            "prediction": "was at Nihed's university, today."
        },
        {
            "prompt_text": "Fajjaaz's truck was at Fajjaaz's highway, 1 days ago. Nihed's boat was at Nihed's park, today. 45 bench were found at park. 15 bench were found at water. Fajjaaz's bench",
            "correct_answer": "park",
            "prediction": "was at Fajjaaz's park, today."
        },
        {
            "prompt_text": "Nihed's boat was at Nihed's park, 1 days ago. Nicole's person was at Nicole's university, today. 27 car were found at garage. 9 car were found at university. Fajjaaz's car",
            "correct_answer": "garage",
            "prediction": "was at Fajjaaz's garage, today."
        },
        {
            "prompt_text": "Nicole's person was at Nicole's university, 1 days ago. Fajjaaz's boat was at Fajjaaz's water, today. 64 motorcycle were found at garage. 10 motorcycle were found at station. Hidde's motorcycle",
            "correct_answer": "garage",
            "prediction": "was at Hidde's water, today."
        },
        {
            "prompt_text": "Fajjaaz's boat was at Fajjaaz's water, 1 days ago. Hidde's car was at Hidde's park, today. 64 motorcycle were found at garage. 10 motorcycle were found at station. Hidde's motorcycle",
            "correct_answer": "garage",
            "prediction": "was at Hidde's park, today."
        },
        {
            "prompt_text": "Hidde's car was at Hidde's park, 1 days ago. Nihed's bench was at Nihed's park, today. 38 boat were found at water. 9 boat were found at park. Fajjaaz's boat",
            "correct_answer": "water",
            "prediction": "was at Fajjaaz's park, today."
        },
        {
            "prompt_text": "Nihed's bench was at Nihed's park, 1 days ago. Nihed's car was at Nihed's garage, today. 64 motorcycle were found at garage. 10 motorcycle were found at station. Taewoon's motorcycle",
            "correct_answer": "garage",
            "prediction": "was at Taewoon's garage, today."
        },
        {
            "prompt_text": "Nihed's bench was at Nihed's park, today. 27 truck were found at highway. 12 truck were found at garage. Nihed's truck",
            "correct_answer": "water",
            "prediction": "was at Nihed's park, today."
        },
        {
            "prompt_text": "Nihed's bench was at Nihed's park, 1 days ago. Nihed's airplane was at Nihed's garage, today. 37 bus were found at station. 9 bus were found at park. Hidde's bus",
            "correct_answer": "station",
            "prediction": "was at Hidde's park, today."
        },
        {
            "prompt_text": "Nihed's airplane was at Nihed's garage, 1 days ago. Fajjaaz's bench was at Fajjaaz's garage, today. 64 motorcycle were found at garage. 10 motorcycle were found at station. Hidde's motorcycle",
            "correct_answer": "garage",
            "prediction": "was at Hidde's garage, today."
        },
        {
            "prompt_text": "Fajjaaz's bench was at Fajjaaz's garage, 1 days ago. Nihed's car was at Nihed's highway, today. 49 bench were found at park. 15 bench were found at water. Nihed's bench",
            "correct_answer": "park",
            "prediction": "was at Nihed's highway, today."
        },
        {
            "prompt_text": "Nihed's car was at Nihed's highway, 1 days ago. Hidde's airplane was at Hidde's sky, today. 27 truck were found at highway. 12 truck were found at garage. Taewoon's truck",
            "correct_answer": "highway",
            "prediction": "was at Taewoon's highway, today."
        },
        {
            "prompt_text": "Hidde's airplane was at Hidde's sky, 1 days ago. Nicole's person was at Nicole's university, today. 38 boat were found at water. 9 boat were found at park. Fajjaaz's boat",
            "correct_answer": "water",
            "prediction": "was at Fajjaaz's water, today."
        },
        {
            "prompt_text": "Nicole's person was at Nicole's university, 1 days ago. Nicole's bench was at Nicole's highway, today. 38 boat were found at water. 9 boat were found at park. Fajjaaz's boat",
            "correct_answer": "water",
            "prediction": "was at Fajjaaz's park, today."
        },
        {
            "prompt_text": "Nicole's bench was at Nicole's highway, today. 51 person were found at university. 7 person were found at water. Nicole's person",
            "correct_answer": "university",
            "prediction": "was found at university."
        },
        {
            "prompt_text": "Nicole's bench was at Nicole's highway, 1 days ago. Hidde's boat was at Hidde's water, today. 39 boat were found at water. 9 boat were found at park. Nicole's boat",
            "correct_answer": "garage",
            "prediction": "was at Nicole's water, today."
        },
        {
            "prompt_text": "Hidde's boat was at Hidde's water, 1 days ago. Hidde's bicycle was at Hidde's university, today. 28 bicycle were found at garage. 9 bicycle were found at highway. Taewoon's bicycle",
            "correct_answer": "garage",
            "prediction": "was at Taewoon's university, today."
        },
        {
            "prompt_text": "Hidde's bicycle was at Hidde's university, 1 days ago. Nicole's boat was at Nicole's sky, today. 40 train were found at station. 15 train were found at water. Taewoon's train",
            "correct_answer": "station",
            "prediction": "was at Taewoon's station, 1 days ago."
        },
        {
            "prompt_text": "Nicole's boat was at Nicole's sky, 1 days ago. Nihed's motorcycle was at Nihed's garage, today. 37 bus were found at station. 9 bus were found at park. Nihed's bus",
            "correct_answer": "sky",
            "prediction": "was at Nihed's garage, today."
        },
        {
            "prompt_text": "Nihed's motorcycle was at Nihed's garage, 1 days ago. Nicole's airplane was at Nicole's sky, today. 46 airplane were found at sky. 11 airplane were found at highway. Nihed's airplane",
            "correct_answer": "garage",
            "prediction": "was at Nihed's sky, today."
        },
        {
            "prompt_text": "Nicole's airplane was at Nicole's sky, 1 days ago. Nicole's person was at Nicole's university, today. 52 person were found at university. 7 person were found at water. Taewoon's person",
            "correct_answer": "water",
            "prediction": "was at Taewoon's university, today."
        },
        {
            "prompt_text": "Nicole's person was at Nicole's university, 1 days ago. Fajjaaz's motorcycle was at Fajjaaz's station, today. 40 boat were found at water. 9 boat were found at park. Nihed's boat",
            "correct_answer": "park",
            "prediction": "was at Nihed's station, today."
        },
        {
            "prompt_text": "Fajjaaz's motorcycle was at Fajjaaz's station, 1 days ago. Hidde's car was at Hidde's park, today. 27 truck were found at highway. 12 truck were found at garage. Fajjaaz's truck",
            "correct_answer": "highway",
            "prediction": "was at Fajjaaz's station, 1 days ago. Hidde'"
        },
        {
            "prompt_text": "Hidde's car was at Hidde's park, 1 days ago. Nihed's person was at Nihed's water, today. 53 person were found at university. 8 person were found at water. Nihed's person",
            "correct_answer": "water",
            "prediction": "was at Nihed's water, today."
        },
        {
            "prompt_text": "Nihed's person was at Nihed's water, 1 days ago. Nihed's bicycle was at Nihed's garage, today. 49 bench were found at park. 15 bench were found at water. Nicole's bench",
            "correct_answer": "highway",
            "prediction": "was at Nicole's water, 1 days ago."
        },
        {
            "prompt_text": "Nihed's bicycle was at Nihed's garage, 1 days ago. Hidde's bench was at Hidde's sky, today. 28 car were found at garage. 9 car were found at university. Taewoon's car",
            "correct_answer": "garage",
            "prediction": "was at Taewoon's garage, 1 days ago."
        },
        {
            "prompt_text": "Hidde's bench was at Hidde's sky, 1 days ago. Fajjaaz's train was at Fajjaaz's station, today. 28 car were found at garage. 9 car were found at university. Nihed's car",
            "correct_answer": "highway",
            "prediction": "was at Nihed's sky, 1 days ago."
        },
        {
            "prompt_text": "Fajjaaz's train was at Fajjaaz's station, 1 days ago. Fajjaaz's boat was at Fajjaaz's water, today. 27 truck were found at highway. 12 truck were found at garage. Fajjaaz's truck",
            "correct_answer": "highway",
            "prediction": "was at Fajjaaz's highway, today."
        },
        {
            "prompt_text": "Fajjaaz's boat was at Fajjaaz's water, 1 days ago. Nicole's bench was at Nicole's park, today. 27 truck were found at highway. 12 truck were found at garage. Fajjaaz's truck",
            "correct_answer": "highway",
            "prediction": "was at Fajjaaz's water, 1 days ago."
        },
        {
            "prompt_text": "Nicole's bench was at Nicole's park, 1 days ago. Nicole's person was at Nicole's sky, today. 42 train were found at station. 15 train were found at water. Hidde's train",
            "correct_answer": "station",
            "prediction": "was at Hidde's station, 1 days ago."
        },
        {
            "prompt_text": "Nicole's person was at Nicole's sky, today. 28 car were found at garage. 9 car were found at university. Hidde's car",
            "correct_answer": "park",
            "prediction": "was found at university."
        },
        {
            "prompt_text": "Nicole's person was at Nicole's sky, 1 days ago. Nihed's truck was at Nihed's highway, today. 28 car were found at garage. 9 car were found at university. Hidde's car",
            "correct_answer": "park",
            "prediction": "was at Hidde's highway, today."
        },
        {
            "prompt_text": "Nihed's truck was at Nihed's highway, 1 days ago. Nihed's bus was at Nihed's highway, today. 53 person were found at university. 9 person were found at water. Taewoon's person",
            "correct_answer": "water",
            "prediction": "was found at water."
        },
        {
            "prompt_text": "Nihed's bus was at Nihed's highway, 1 days ago. Taewoon's boat was at Taewoon's station, today. 30 bicycle were found at garage. 9 bicycle were found at university. Fajjaaz's bicycle",
            "correct_answer": "university",
            "prediction": "was at Fajjaaz's highway, 1 days ago."
        },
        {
            "prompt_text": "Taewoon's boat was at Taewoon's station, 1 days ago. Nihed's bus was at Nihed's station, today. 42 boat were found at water. 9 boat were found at park. Nicole's boat",
            "correct_answer": "sky",
            "prediction": "was at Nicole's station, today."
        },
        {
            "prompt_text": "Nihed's bus was at Nihed's station, 1 days ago. Hidde's airplane was at Hidde's station, today. 28 car were found at garage. 9 car were found at university. Taewoon's car",
            "correct_answer": "garage",
            "prediction": "was at Taewoon's station, today."
        },
        {
            "prompt_text": "Hidde's airplane was at Hidde's station, 1 days ago. Nicole's motorcycle was at Nicole's garage, today. 47 airplane were found at sky. 13 airplane were found at station. Hidde's airplane",
            "correct_answer": "station",
            "prediction": "was at Hidde's station"
        }
    ]
}