[{"turn": 0, "speaker": "speaker1", "text": "It seems that you get antsy when you hear I praise another guy . ", "speech-act": "command", "given_emotion": 0, "given_act": 1, "rdf_file": []}, {"turn": 1, "speaker": "speaker2", "text": " I get antsy not because you praise a guy , but because you may be taken for a ride by a guy like him . ", "speech-act": "statement", "given_emotion": 2, "given_act": 1, "rdf_file": ["brain_log_2022-12-14-11-10-34"]}, {"turn": 2, "speaker": "speaker1", "text": " How come you think of him that way ? ", "speech-act": "open_question_opinion", "given_emotion": 0, "given_act": 2, "rdf_file": ["brain_log_2022-12-14-11-10-35"]}, {"turn": 3, "speaker": "speaker2", "text": " Because you seem to have lost your vigilance . You should be on the watch out . ", "speech-act": "opinion", "given_emotion": 2, "given_act": 1, "rdf_file": ["brain_log_2022-12-14-11-10-35", "brain_log_2022-12-14-11-10-35"]}, {"turn": 4, "speaker": "speaker1", "text": " I have no reason to distrust him . He's never caused any harm . ", "speech-act": "statement", "given_emotion": 0, "given_act": 1, "rdf_file": ["brain_log_2022-12-14-11-10-36", "brain_log_2022-12-14-11-10-36", "brain_log_2022-12-14-11-10-36"]}, {"turn": 5, "speaker": "speaker2", "text": " Isn't there anything that sounds fishy ? ", "speech-act": "yes_no_question", "given_emotion": 1, "given_act": 2, "rdf_file": ["brain_log_2022-12-14-11-10-37", "brain_log_2022-12-14-11-10-37", "brain_log_2022-12-14-11-10-37"]}, {"turn": 6, "speaker": "speaker1", "text": " Nothing smells a rat . I told you that he's an all-right guy . ", "speech-act": "statement", "given_emotion": 0, "given_act": 1, "rdf_file": ["brain_log_2022-12-14-11-10-37", "brain_log_2022-12-14-11-10-38", "brain_log_2022-12-14-11-10-38", "brain_log_2022-12-14-11-10-39"]}, {"turn": 7, "speaker": "speaker2", "text": " All-right guy ? All right . Let's talk about something else instead . ", "speech-act": "command", "given_emotion": 6, "given_act": 2, "rdf_file": ["brain_log_2022-12-14-11-10-40", "brain_log_2022-12-14-11-10-41", "brain_log_2022-12-14-11-10-41", "brain_log_2022-12-14-11-10-42"]}]