[{"Turn": 0, "Speaker": "speaker1", "Response": "What do you do in your free time , Nancy ? ", "speech-act": "open_question_factual", "given_emotion": 0, "given_act": 2, "rdf_file": ["brain_log_2022-12-14-11-46-08"]}, {"Turn": 1, "Speaker": "speaker2", "Response": " Well , I like playing the violin . ", "speech-act": "opinion", "given_emotion": 0, "given_act": 1, "rdf_file": ["brain_log_2022-12-14-11-46-09"]}, {"Turn": 2, "Speaker": "speaker1", "Response": " Really ? How long have you been playing the violin ? ", "speech-act": "open_question_factual", "given_emotion": 0, "given_act": 2, "rdf_file": ["brain_log_2022-12-14-11-46-09", "brain_log_2022-12-14-11-46-10"]}, {"Turn": 3, "Speaker": "speaker2", "Response": " About ten years so far . I started learning when I was in middle school . ", "speech-act": "statement", "given_emotion": 0, "given_act": 1, "rdf_file": ["brain_log_2022-12-14-11-46-10", "brain_log_2022-12-14-11-46-10"]}, {"Turn": 4, "Speaker": "speaker1", "Response": " That's really interesting . ", "speech-act": "appreciation", "given_emotion": 4, "given_act": 1, "rdf_file": ["brain_log_2022-12-14-11-46-11", "brain_log_2022-12-14-11-46-12"]}, {"Turn": 5, "Speaker": "speaker2", "Response": " Sure . So what about you ? Do you have any hobbies ? ", "speech-act": "pos_answer", "given_emotion": 4, "given_act": 2, "rdf_file": ["brain_log_2022-12-14-11-46-13", "brain_log_2022-12-14-11-46-13", "brain_log_2022-12-14-11-46-14"]}, {"Turn": 6, "Speaker": "speaker1", "Response": " Well , I like collecting matchbox ! I'm not sure if that counts , though . ", "speech-act": "opinion", "given_emotion": 4, "given_act": 1, "rdf_file": ["brain_log_2022-12-14-11-46-15", "brain_log_2022-12-14-11-46-16", "brain_log_2022-12-14-11-46-16", "brain_log_2022-12-14-11-46-18"]}, {"Turn": 7, "Speaker": "speaker2", "Response": " Of course it does . Everybody has his own hobby . ", "speech-act": "opinion", "given_emotion": 4, "given_act": 1, "rdf_file": ["brain_log_2022-12-14-11-46-19", "brain_log_2022-12-14-11-46-19", "brain_log_2022-12-14-11-46-20", "brain_log_2022-12-14-11-46-21"]}]