[{"Turn": 0, "Speaker": "participant2", "Response": "i am a little tired from work", "speech-act": "statement", "rdf_file": ["brain_log_2022-12-14-13-22-02"]}, {"Turn": 1, "Speaker": "participant1", "Response": "hi!", "speech-act": "opening", "rdf_file": ["brain_log_2022-12-14-13-22-02"]}, {"Turn": 2, "Speaker": "participant2", "Response": "/start", "speech-act": "closing", "rdf_file": ["brain_log_2022-12-14-13-22-03"]}, {"Turn": 3, "Speaker": "participant1", "Response": "hello", "speech-act": "abandon", "rdf_file": ["brain_log_2022-12-14-13-22-03"]}, {"Turn": 4, "Speaker": "participant2", "Response": "i play video games , and play video games , and play video games .", "speech-act": "statement", "rdf_file": ["brain_log_2022-12-14-13-22-04", "brain_log_2022-12-14-13-22-04"]}, {"Turn": 5, "Speaker": "participant1", "Response": "me too", "speech-act": "opinion", "rdf_file": ["brain_log_2022-12-14-13-22-05", "brain_log_2022-12-14-13-22-05"]}, {"Turn": 6, "Speaker": "participant2", "Response": "that is cool , i am a teacher , and i am a teacher , and you ?", "speech-act": "statement", "rdf_file": ["brain_log_2022-12-14-13-22-05", "brain_log_2022-12-14-13-22-06", "brain_log_2022-12-14-13-22-06"]}, {"Turn": 7, "Speaker": "participant1", "Response": "me too", "speech-act": "statement", "rdf_file": ["brain_log_2022-12-14-13-22-06", "brain_log_2022-12-14-13-22-07", "brain_log_2022-12-14-13-22-07"]}, {"Turn": 8, "Speaker": "participant2", "Response": "i am a teacher , and i am a teacher , and you ?", "speech-act": "statement", "rdf_file": ["brain_log_2022-12-14-13-22-07", "brain_log_2022-12-14-13-22-08", "brain_log_2022-12-14-13-22-08", "brain_log_2022-12-14-13-22-08"]}]